dec_bi_conv/__init__.py
dec_bi_conv/converter.py
decimal_binary_converter-0.1.0.dist-info/METADATA
decimal_binary_converter-0.1.0.dist-info/WHEEL
decimal_binary_converter-0.1.0.dist-info/top_level.txt
decimal_binary_converter-0.1.0.dist-info/RECORD
