Metadata-Version: 2.1
Name: decimal_binary_converter
Version: 0.1.0
Summary: Convert decimal numbers to binary and binary to decimal in Python.
Author-email: Your Name <your.email@example.com>
Requires-Python: >=3.7
